pyed/__init__.py
pyed/utils.py
pyed/version.py
pyed/core/__init__.py
pyed/core/constants.py
pyed/core/dict_parser.py
pyed/core/node.py
pyed/core/utils.py
pyed/core/xml_item.py
pyed/core/tests/test_parser.py
pyed/core/tests/test_utils.py
pyed/elements/__init__.py
pyed/elements/edge.py
pyed/elements/generic_node.py
pyed/elements/graph.py
pyed/elements/group.py
pyed/elements/label.py
pyed/elements/resource.py
pyed/elements/shape_node.py
pyed/elements/svg_node.py
pyed/elements/table_node.py
pyed/elements/uml_node.py
pyed/elements/tests/custom_node_shape.svg
pyed/elements/tests/test_edge.py
pyed/elements/tests/test_genericnode.py
pyed/elements/tests/test_graph.py
pyed/elements/tests/test_group.py
pyed/elements/tests/test_label.py
pyed/elements/tests/test_resource.py
pyed/elements/tests/test_shapenode.py
pyed/elements/tests/test_svgnode.py
pyed/elements/tests/test_tablenode.py
pyed/elements/tests/test_umlnode.py
pyed-1.2.5.dist-info/licenses/LICENSE.txt
pyed-1.2.5.dist-info/METADATA
pyed-1.2.5.dist-info/WHEEL
pyed-1.2.5.dist-info/top_level.txt
pyed-1.2.5.dist-info/RECORD
