Metadata-Version: 2.4
Name: pyed
Version: 1.2.5
Summary: Python Yed Simple Graph generator
Author-email: Christophe Cossou <ccossou@gmail.com>
License: MIT License
Project-URL: homepage, https://github.com/ccossou/Pyed
Project-URL: documentation, https://pyed.readthedocs.io
Project-URL: source, https://github.com/ccossou/Pyed
Project-URL: tracker, https://github.com/ccossou/Pyed/issues
Classifier: Programming Language :: Python
Classifier: Programming Language :: Python :: 3
Classifier: Programming Language :: Python :: 3.9
Classifier: Programming Language :: Python :: 3.10
Classifier: Programming Language :: Python :: 3.11
Classifier: Programming Language :: Python :: 3.12
Classifier: Programming Language :: Python :: 3 :: Only
Classifier: Operating System :: Microsoft :: Windows
Classifier: Operating System :: Unix
Classifier: Operating System :: MacOS
Requires-Python: >=3.9
License-File: LICENSE.txt
Requires-Dist: pytest
Requires-Dist: setuptools
Requires-Dist: pyyaml
Dynamic: license-file
